<?xml version="1.0" encoding="UTF-8"?>    
<christ>
   <computerscience>
        <name>Athira</name>
        <university>Christ University</university>
        <phone>7676767679</phone>
        <email>athira@christuniversity.in</email>
    </computerscience>
    <computerscience>
        <name>Vishwanath</name>
        <university>Neelgiri College</university>
        <phone>7509263820</phone>
        <email>vishwa@neeluniversity.com</email>
    </computerscience>
    <computerscience>
        <name>Kushagra</name>
        <university>New Horizon </university>
        <phone>8264319097</phone>
        <email>Kushagra@newhorizon.com</email>
    </computerscience>
</christ>
